agora_config/__init__.py
agora_config/agora_config.py
agora_config/command_line_provider.py
agora_config/dict_of_dict.py
agora_config/environment_variable_provider.py
agora_config/file_key_provider.py
agora_config/file_provider.py
agora_config/last_value_callbacks.py
agora_config/version.py
agora_config-3.0.2.dist-info/licenses/LICENSE
agora_config-3.0.2.dist-info/WHEEL
agora_config-3.0.2.dist-info/METADATA
agora_config-3.0.2.dist-info/RECORD
