Metadata-Version: 2.4
Name: agora_config
Version: 3.0.2
Summary: Configuration libraries for the Agora Edge Apps SDK 2.0 (Python)
Author-email: AgoraIoT <agoraiot@slb.com>
Classifier: License :: OSI Approved :: Apache Software License
License-File: LICENSE
Requires-Dist: agora_logging == 3.0.2
Requires-Dist: termcolor == 2.4.0
Project-URL: Home, https://agoraiot.github.io
